[
  {
    "candidate": "anchor",
    "split": "train",
    "label": "Train",
    "date_start": "2012-05-15",
    "date_end": "2020-03-31",
    "row_count": 36279,
    "code_count": 28,
    "rel_score": 0.010297289326997028,
    "directional_accuracy": 0.44072328344221173,
    "error_q2": -0.01219332532,
    "error_q8": 0.011242264218,
    "error_mean": -0.0004077153287371382,
    "error_std": 0.019740994518462653,
    "proxy_mean": 0.5583135436192883,
    "proxy_median": 0.6475752364935532,
    "proxy_positive_share": 0.9166459935499875,
    "proxy_hard_left_share": 8.269246671628214e-05
  },
  {
    "candidate": "anchor",
    "split": "val",
    "label": "In-sample",
    "date_start": "2020-04-01",
    "date_end": "2022-11-15",
    "row_count": 18279,
    "code_count": 28,
    "rel_score": 0.005339846340188692,
    "directional_accuracy": 0.4885387603260572,
    "error_q2": -0.01604447644,
    "error_q8": 0.013328037260000002,
    "error_mean": -0.0008031363713562082,
    "error_std": 0.02365254646512561,
    "proxy_mean": 0.5569069425123044,
    "proxy_median": 0.6453336706282593,
    "proxy_positive_share": 0.9166256359757098,
    "proxy_hard_left_share": 5.470758794244762e-05
  },
  {
    "candidate": "sector19_down_up_anchor_else",
    "split": "train",
    "label": "Train",
    "date_start": "2012-05-15",
    "date_end": "2020-03-31",
    "row_count": 36279,
    "code_count": 28,
    "rel_score": 0.008952109719460699,
    "directional_accuracy": 0.44039251357534664,
    "error_q2": -0.012363154559999999,
    "error_q8": 0.011180544700000001,
    "error_mean": -0.0005798987646742715,
    "error_std": 0.0197333003860452,
    "proxy_mean": 0.557899730956249,
    "proxy_median": 0.6463002122770632,
    "proxy_positive_share": 0.9175280465282946,
    "proxy_hard_left_share": 5.5128311144188097e-05
  },
  {
    "candidate": "sector19_down_up_anchor_else",
    "split": "val",
    "label": "In-sample",
    "date_start": "2020-04-01",
    "date_end": "2022-11-15",
    "row_count": 18279,
    "code_count": 28,
    "rel_score": 0.0033873307888869775,
    "directional_accuracy": 0.48684282509984134,
    "error_q2": -0.016316452794,
    "error_q8": 0.01307827656000001,
    "error_mean": -0.0011139610020807912,
    "error_std": 0.023611095158109337,
    "proxy_mean": 0.5571244604393919,
    "proxy_median": 0.6453649957932801,
    "proxy_positive_share": 0.9184309863778106,
    "proxy_hard_left_share": 0.0
  },
  {
    "candidate": "train_rank_regime_ic_weight",
    "split": "train",
    "label": "Train",
    "date_start": "2012-05-15",
    "date_end": "2020-03-31",
    "row_count": 36279,
    "code_count": 28,
    "rel_score": 0.009640000340884747,
    "directional_accuracy": 0.44210149122081643,
    "error_q2": -0.012347298474799998,
    "error_q8": 0.011142928677740001,
    "error_mean": -0.0005710399099365114,
    "error_std": 0.019713435836897733,
    "proxy_mean": 0.5587827591255269,
    "proxy_median": 0.6462930665059847,
    "proxy_positive_share": 0.919402409107197,
    "proxy_hard_left_share": 2.7564155572094048e-05
  },
  {
    "candidate": "train_rank_regime_ic_weight",
    "split": "val",
    "label": "In-sample",
    "date_start": "2020-04-01",
    "date_end": "2022-11-15",
    "row_count": 18279,
    "code_count": 28,
    "rel_score": 0.003667655712425555,
    "directional_accuracy": 0.4835603698232945,
    "error_q2": -0.016318957480199996,
    "error_q8": 0.013010778666800012,
    "error_mean": -0.0011140368810427037,
    "error_std": 0.02361956795262618,
    "proxy_mean": 0.5570611023545927,
    "proxy_median": 0.6455780599284782,
    "proxy_positive_share": 0.917500957382789,
    "proxy_hard_left_share": 0.0
  }
]