{
  "lstm": {
    "ranked_models": [
      {
        "model": "lstm_seed_62",
        "val_score": 0.00771424312579283,
        "test_score": -0.016462026845680544
      },
      {
        "model": "lstm_seed_52",
        "val_score": 0.0022536852475300018,
        "test_score": -0.015506398065137983
      },
      {
        "model": "lstm_seed_42",
        "val_score": 0.0021573793309326295,
        "test_score": -0.01354843618775714
      }
    ],
    "best_by_val": "lstm_seed_62",
    "top2_by_val": [
      "lstm_seed_62",
      "lstm_seed_52"
    ]
  },
  "lstm_signmag": {
    "ranked_models": [
      {
        "model": "lstm_signmag_seed_62",
        "val_score": 0.016401289343479175,
        "test_score": -0.016167891868073436
      },
      {
        "model": "lstm_signmag_seed_52",
        "val_score": 0.014767072917382218,
        "test_score": -0.017606331971032674
      },
      {
        "model": "lstm_signmag_seed_42",
        "val_score": 0.009731962283748063,
        "test_score": -0.021929950969208356
      }
    ],
    "best_by_val": "lstm_signmag_seed_62",
    "top2_by_val": [
      "lstm_signmag_seed_62",
      "lstm_signmag_seed_52"
    ]
  }
}